lamuda/__init__.py
lamuda/misc/__init__.py
lamuda/misc/utils.py
lamuda-20.1.1.dist-info/LICENSE
lamuda-20.1.1.dist-info/METADATA
lamuda-20.1.1.dist-info/WHEEL
lamuda-20.1.1.dist-info/top_level.txt
lamuda-20.1.1.dist-info/RECORD
